bluescan/__init__.py
bluescan/__main__.py
bluescan-0.8.10.dist-info/LICENSE.txt
bluescan-0.8.10.dist-info/METADATA
bluescan-0.8.10.dist-info/WHEEL
bluescan-0.8.10.dist-info/entry_points.txt
bluescan-0.8.10.dist-info/top_level.txt
bluescan-0.8.10.dist-info/RECORD
